geojson_serializer/__init__.py
geojson_serializer/admin.py
geojson_serializer/apps.py
geojson_serializer/models.py
geojson_serializer/serializers.py
geojson_serializer/tests.py
geojson_serializer/views.py
geojson_serializer/migrations/__init__.py
django_geojson_serializer-0.3.dist-info/LICENSE
django_geojson_serializer-0.3.dist-info/METADATA
django_geojson_serializer-0.3.dist-info/WHEEL
django_geojson_serializer-0.3.dist-info/top_level.txt
django_geojson_serializer-0.3.dist-info/RECORD
