Metadata-Version: 2.1
Name: django-geojson-serializer
Version: 0.3
Summary: Geojson serializer decorator for django rest framework
Home-page: https://github.com/pglotov/django-geojson_serializer
Author: Petr Glotov
Author-email: pglotov@yahoo.com
License: BSD License
Platform: UNKNOWN
Classifier: Environment :: Web Environment
Classifier: Framework :: Django
Classifier: Intended Audience :: Developers
Classifier: License :: OSI Approved :: BSD License
Classifier: Operating System :: OS Independent
Classifier: Programming Language :: Python
Classifier: Programming Language :: Python :: 3
Classifier: Programming Language :: Python :: 3.4
Classifier: Programming Language :: Python :: 3.5
Classifier: Topic :: Internet :: WWW/HTTP
Classifier: Topic :: Internet :: WWW/HTTP :: Dynamic Content
